debian_parser/__init__.py
debian_parser/__version__.py
debian_parser/parser.py
debian_parser-0.1.2.dist-info/LICENSE
debian_parser-0.1.2.dist-info/METADATA
debian_parser-0.1.2.dist-info/WHEEL
debian_parser-0.1.2.dist-info/top_level.txt
debian_parser-0.1.2.dist-info/RECORD
