Metadata-Version: 2.1
Name: debian-parser
Version: 0.1.2
Summary: A simple pure-python module to parse RFC822-like Debain data formats. Including Pacakges, Control, Release files.
Home-page: https://github.com/ms7m/debian-packages-parser
Author: Mustafa Mohamed
Author-email: ms7mohamed@gmail.com
License: GNU
Platform: UNKNOWN
Classifier: License :: OSI Approved :: GNU General Public License v3 (GPLv3)
Classifier: Programming Language :: Python
Classifier: Programming Language :: Python :: 3
Classifier: Programming Language :: Python :: 3.6
Classifier: Programming Language :: Python :: Implementation :: CPython
Classifier: Programming Language :: Python :: Implementation :: PyPy
Requires-Python: >=3.6.0
